{
  "name": "Frederick Buchanan",
  "age": 62,
  "address": {
    "street": "Toje Glen",
    "city": "Ifdapzoj",
    "state": "NY",
    "zip": "36100"
  },
  "contact": {
    "phone": "(967) 536-6017",
    "servicePhone": "800673874"
  },
  "birthday": "1959-02-20T17:34:29.896Z",
  "ip": "81.156.190.54",
  "foo": "bar",
  "profile": {
    "about": "Pe powa hucac zo mi ca gibamew anidamun gevut vugpezgu tudgow helru. Sepfe re kuvaddup cin okaficmo kemehinib ja hidsur heh isiko fujsam vuazpo emvazu zalnowop ahu cipiiw banoar. Rizare zof julce pumtemob ceopouz getsazes bovumam ehejaw wed war sir gin wahetge tetdum kolahdol.",
    "bio": "Culrigig muji pewufu weg dokip pozza rojkec tur megisot ohpi linnecto irozolil wuvedur devvok gicil wimazrav tenetu. Jotipjaw zultuj vocis la iza so gicbepoh koh hu gehemto aw vein. Nuvetlav tugis na on fus jemewte jesnigvih ol itra esfe ge nuvhewu kuhija cujabjop fahpal ezjag jipudru. Mu miswig zimohunu rec jic ga ze dabmelhan ukba fojuda dunahko wakasbi nuva puhejgi. Kofu cukna mow ugkub se ejmod guwom nujasane cof zun koogze luife pej jadpo zijuw. Hifuj la notifpav reb keg ufi toaco wookowo kuzmuvkaz ju labafihu seba wiwmilha jajan we tinaze bulifejus zipjeb. Sagon bosuwuwu gucno najruv gotihten ze egbir dohewa caja wafakron ul evuwafof."
  },
  "apiKey": "d6267cc56c718416cdcfc094c1459b58d0e6d8942e62607f466ee75e1d81744e",
  "currency": {
    "code": "BWP",
    "name": "Botswana Pula"
  }
}